dan/__init__.py
dan/model.py
dan/stage.py
dan/utils.py
dan/layers/__init__.py
dan/layers/affine_image.py
dan/layers/affine_landmark.py
dan/layers/estimate_param.py
dan/layers/heatmap_layer.py
tests/__init__.py
tests/test_model.py
tests/test_stage.py
tests/test_utils.py
tests/layers/__init__.py
tests/layers/test_affine_image.py
tests/layers/test_affine_landmark.py
tests/layers/test_estimate_param.py
tests/layers/test_heatmap_layer.py
deep_alignment_pytorch-0.1.0.dist-info/LICENSE
deep_alignment_pytorch-0.1.0.dist-info/METADATA
deep_alignment_pytorch-0.1.0.dist-info/WHEEL
deep_alignment_pytorch-0.1.0.dist-info/top_level.txt
deep_alignment_pytorch-0.1.0.dist-info/RECORD
