Metadata-Version: 2.1
Name: deep-alignment-pytorch
Version: 0.1.0
Summary: UNKNOWN
Home-page: https://github.com/justussschock/deep_alignment_network_pytorch
Author: Justus Schock
Author-email: justus.schock@rwth-aachen.de
License: BSD 2-Clause License
Requires-Dist: delira[torch]
Requires-Dist: shapedata
Requires-Dist: torch-layers
